{
  "$description": "| What does this do? | SharePoint and OneDrive integration with Azure AD B2B is enabled; OneDrive content sharing is restricted; link sharing is restricted in SharePoint and OneDrive; guest access to a site or OneDrive will expire automatically; reauthentication with verification code is restricted; Office 365 SharePoint infected files are disallowed for download. |\n| Why should you use this? | Having these settings reduces the chances of data exfiltration in your organization. |\n| What is the end-user impact? | Users will only be able to share SharePoint Online content with guest users that already exist in the organization; users will only be able to share OneDrive for Business content with other member users. |\n| Learn more | [Turn external sharing off](https://learn.microsoft.com/en-us/sharepoint/turn-external-sharing-on-or-off) [Sharepoint Online](https://learn.microsoft.com/en-us/powershell/module/sharepoint-online/set-spotenant?view=sharepoint-ps) [SharePoint Azure B2B integration](https://learn.microsoft.com/en-us/sharepoint/sharepoint-azureb2b-integration#enabling-the-integration) |",
  "$friendlyName": "Configuration",
  "AllowCommentsTextOnEmailEnabled": true,
  "AllowDownloadingNonWebViewableFiles": true,
  "AllowEditing": true,
  "AllowGuestUserShareToUsersNotInSiteCollection": false,
  "AllowLimitedAccessOnUnmanagedDevices": false,
  "AllowOverrideForBlockUserInfoVisibility": false,
  "AllowedDomainListForSyncClient": [],
  "AnyoneLinkTrackUsers": false,
  "ApplyAppEnforcedRestrictionsToAdHocRecipients": true,
  "BccExternalSharingInvitations": false,
  "BlockAccessOnUnmanagedDevices": false,
  "BlockDownloadLinksFileType": "WebPreviewableFiles",
  "BlockDownloadOfAllFilesForGuests": false,
  "BlockDownloadOfAllFilesOnUnmanagedDevices": false,
  "BlockDownloadOfViewableFilesForGuests": false,
  "BlockDownloadOfViewableFilesOnUnmanagedDevices": false,
  "BlockMacSync": true,
  "BlockSendLabelMismatchEmail": false,
  "BlockUserInfoVisibilityInOneDrive": "ApplyToGuestAndExternalUsers",
  "BlockUserInfoVisibilityInSharePoint": "ApplyToNoUsers",
  "CommentsOnFilesDisabled": false,
  "CommentsOnListItemsDisabled": false,
  "CommentsOnSitePagesDisabled": false,
  "ConditionalAccessPolicy": "AllowFullAccess",
  "ConditionalAccessPolicyErrorHelpLink": "",
  "ContentTypeSyncSiteTemplatesList": [],
  "CustomizedExternalSharingServiceUrl": "",
  "DefaultLinkPermission": "Edit",
  "DefaultODBMode": "Explicit",
  "DefaultSharingLinkType": "Direct",
  "DisableAddToOneDrive": false,
  "DisableBackToClassic": false,
  "DisableCustomAppAuthentication": true,
  "DisableOutlookPSTVersionTrimming": false,
  "DisablePersonalListCreation": false,
  "DisableReportProblemDialog": false,
  "DisableSpacesActivation": false,
  "DisabledModernListTemplateIds": [],
  "DisallowInfectedFileDownload": true,
  "DisplayNamesOfFileViewers": true,
  "DisplayNamesOfFileViewersInSpo": true,
  "DisplayStartASiteOption": true,
  "EmailAttestationEnabled": true,
  "EmailAttestationReAuthDays": 15,
  "EmailAttestationRequired": true,
  "EnableAIPIntegration": false,
  "EnableAutoNewsDigest": true,
  "EnableAzureADB2BIntegration": true,
  "EnableGuestSignInAcceleration": false,
  "EnableMinimumVersionRequirement": true,
  "EnableMipSiteLabel": false,
  "EnablePromotedFileHandlers": true,
  "ExcludedFileExtensionsForSyncClient": [
    ""
  ],
  "ExternalServicesEnabled": true,
  "ExternalUserExpirationRequired": true,
  "ExternalUserExpireInDays": 30,
  "FileAnonymousLinkType": "Edit",
  "FilePickerExternalImageSearchEnabled": true,
  "FolderAnonymousLinkType": "Edit",
  "GuestSharingGroupAllowListInTenantAcl": {
    "AccessControlEntries": [
      {
        "AllowRights": "3",
        "DenyRights": "0",
        "DisplayName": "0o.c|federateddirectoryclaimprovider|7c1a429c-e9bb-4458-ac3e-f1921088b391",
        "IdentityName": "c:0o.c|federateddirectoryclaimprovider|7c1a429c-e9bb-4458-ac3e-f1921088b391",
        "Sid": ""
      }
    ]
  },
  "GuestSharingGroupAllowListInTenantByPrincipalIdentity": [
    "c:0o.c|federateddirectoryclaimprovider|7c1a429c-e9bb-4458-ac3e-f1921088b391"
  ],
  "HasAdminCompletedCUConfiguration": false,
  "HasIntelligentContentServicesCapability": false,
  "HasTopicExperiencesCapability": false,
  "HideSyncButtonOnDocLib": false,
  "HideSyncButtonOnODB": false,
  "IPAddressAllowList": "",
  "IPAddressEnforcement": false,
  "IPAddressWACTokenLifetime": 15,
  "ImageTaggingOption": "Basic",
  "IncludeAtAGlanceInShareEmails": true,
  "InformationBarriersSuspension": true,
  "IsAppBarTemporarilyDisabled": false,
  "IsCollabMeetingNotesFluidEnabled": true,
  "IsFluidEnabled": true,
  "IsWBFluidEnabled": true,
  "LimitedAccessFileType": "WebPreviewableFiles",
  "MachineLearningCaptureEnabled": false,
  "MarkNewFilesSensitiveByDefault": "AllowExternalSharing",
  "MediaTranscription": "Enabled",
  "MobileFriendlyUrlEnabledInTenant": true,
  "NotificationsInOneDriveForBusinessEnabled": true,
  "NotificationsInSharePointEnabled": true,
  "NotifyOwnersWhenItemsReshared": true,
  "ODBAccessRequests": "Unspecified",
  "ODBMembersCanShare": "Unspecified",
  "ODBSharingCapability": "Disabled",
  "OfficeClientADALDisabled": false,
  "OneDriveForGuestsEnabled": false,
  "OneDriveStorageQuota": 1048576,
  "OrphanedPersonalSitesRetentionPeriod": 30,
  "OwnerAnonymousNotification": true,
  "ProvisionSharedWithEveryoneFolder": false,
  "PublicCdnAllowedFileTypes": "CSS,EOT,GIF,ICO,JPEG,JPG,JS,MAP,PNG,SVG,TTF,WOFF",
  "PublicCdnEnabled": false,
  "RequireAcceptingAccountMatchInvitedAccount": false,
  "RequireAnonymousLinksExpireInDays": -1,
  "SearchResolveExactEmailOrUPN": false,
  "ShowAllUsersClaim": false,
  "ShowEveryoneClaim": false,
  "ShowEveryoneExceptExternalUsersClaim": true,
  "ShowPeoplePickerSuggestionsForGuestUsers": false,
  "SignInAccelerationDomain": "",
  "SocialBarOnSitePagesDisabled": false,
  "SpecialCharactersStateInFileFolderNames": "Allowed",
  "StopNew2010Workflows": false,
  "StopNew2013Workflows": false,
  "SyncPrivacyProfileProperties": true,
  "UseFindPeopleInPeoplePicker": false,
  "ViewInFileExplorerEnabled": false,
  "ViewersCanCommentOnMediaDisabled": false,
  "WhoCanShareAllowListInTenant": "",
  "Workflow2010Disabled": true
}