{
  "$friendlyName": "Office Apps Administrator",
  "$description": "Can manage Office apps cloud services, including policy and settings management, and manage the ability to select, unselect and publish 'what's new' feature content to end-user's devices.",
  "isEnabled": true,
  "resourceScopes": [
    "/"
  ],
  "rolePermissions": [
    {
      "allowedResourceActions": [
        "microsoft.azure.serviceHealth/allEntities/allTasks",
        "microsoft.azure.supportTickets/allEntities/allTasks",
        "microsoft.office365.messageCenter/messages/read",
        "microsoft.office365.serviceHealth/allEntities/allTasks",
        "microsoft.office365.supportTickets/allEntities/allTasks",
        "microsoft.office365.userCommunication/allEntities/allTasks",
        "microsoft.office365.webPortal/allEntities/standard/read"
      ]
    }
  ],
  "version": "1"
}
