{
  "$friendlyName": "Global",
  "AllowAnonymousUsersToDialOut": false,
  "AllowAnonymousUsersToJoinMeeting": true,
  "AllowAnonymousUsersToStartMeeting": false,
  "AllowBreakoutRooms": true,
  "AllowCartCaptionsScheduling": "DisabledUserOverride",
  "AllowChannelMeetingScheduling": true,
  "AllowCloudRecording": true,
  "AllowEngagementReport": "Enabled",
  "AllowExternalParticipantGiveRequestControl": false,
  "AllowIPAudio": true,
  "AllowIPVideo": true,
  "AllowMeetingReactions": true,
  "AllowMeetingRegistration": true,
  "AllowMeetNow": true,
  "AllowNDIStreaming": false,
  "AllowNetworkConfigurationSettingsLookup": false,
  "AllowOrganizersToOverrideLobbySettings": false,
  "AllowOutlookAddIn": true,
  "AllowParticipantGiveRequestControl": true,
  "AllowPowerPointSharing": true,
  "AllowPrivateMeetingScheduling": true,
  "AllowPrivateMeetNow": true,
  "AllowPSTNUsersToBypassLobby": false,
  "AllowRecordingStorageOutsideRegion": false,
  "AllowSharedNotes": true,
  "AllowTranscription": false,
  "AllowWatermarkForCameraVideo": true,
  "AllowWatermarkForScreenSharing": true,
  "AllowWhiteboard": true,
  "AutoAdmittedUsers": "EveryoneInCompany",
  "AutomaticallyStartCopilot": "Disabled",
  "ChannelRecordingDownload": "Allow",
  "Copilot": "EnabledWithTranscript",
  "CopyRestriction": true,
  "DesignatedPresenterRoleMode": "EveryoneUserOverride",
  "EnrollUserOverride": "Disabled",
  "ExternalMeetingJoin": "EnabledForAnyone",
  "IPAudioMode": "EnabledOutgoingIncoming",
  "IPVideoMode": "EnabledOutgoingIncoming",
  "LiveCaptionsEnabledType": "DisabledUserOverride",
  "LiveInterpretationEnabledType": "DisabledUserOverride",
  "LiveStreamingMode": "Disabled",
  "MediaBitRateKb": 50000,
  "MeetingChatEnabledType": "Enabled",
  "NewMeetingRecordingExpirationDays": 120,
  "PreferredMeetingProviderForIslandsMode": "TeamsAndSfb",
  "RecordingStorageMode": "OneDriveForBusiness",
  "RoomAttributeUserOverride": "Off",
  "ScreenSharingMode": "EntireScreen",
  "SpeakerAttributionMode": "EnabledUserOverride",
  "StreamingAttendeeMode": "Disabled",
  "TeamsCameraFarEndPTZMode": "Disabled",
  "VideoFiltersMode": "AllFilters",
  "VoiceIsolation": "Enabled",
  "WhoCanRegister": "Everyone"
}
